{
  "InfI": {
    "": "pressentir"
  },
  "InfP": {
    "1s": "pressentir",
    "2s": "pressentires",
    "3s": "pressentir",
    "1p": "pressentirmos",
    "2p": "pressentirdes",
    "3p": "pressentirem"
  },
  "Ger": {
    "": "pressentindo"
  },
  "PresI": {
    "1s": "pressinto",
    "2s": "pressentes",
    "3s": "pressente",
    "1p": "pressentimos",
    "2p": "pressentis",
    "3p": "pressentem"
  },
  "PImpI": {
    "1s": "pressentia",
    "2s": "pressentias",
    "3s": "pressentia",
    "1p": "pressentíamos",
    "2p": "pressentíeis",
    "3p": "pressentiam"
  },
  "PPSI": {
    "1s": "pressenti",
    "2s": "pressentiste",
    "3s": "pressentiu",
    "1p": "pressentimos",
    "2p": "pressentistes",
    "3p": "pressentiram"
  },
  "PMQPSI": {
    "1s": "pressentira",
    "2s": "pressentiras",
    "3s": "pressentira",
    "1p": "pressentíramos",
    "2p": "pressentíreis",
    "3p": "pressentiram"
  },
  "FutSI": {
    "1s": "pressentirei",
    "2s": "pressentirás",
    "3s": "pressentirá",
    "1p": "pressentiremos",
    "2p": "pressentireis",
    "3p": "pressentirão"
  },
  "CondS": {
    "1s": "pressentiria",
    "2s": "pressentirias",
    "3s": "pressentiria",
    "1p": "pressentiríamos",
    "2p": "pressentiríeis",
    "3p": "pressentiriam"
  },
  "PresC": {
    "1s": "pressinta",
    "2s": "pressintas",
    "3s": "pressinta",
    "1p": "pressintamos",
    "2p": "pressintais",
    "3p": "pressintam"
  },
  "PImpC": {
    "1s": "pressentisse",
    "2s": "pressentisses",
    "3s": "pressentisse",
    "1p": "pressentíssemos",
    "2p": "pressentísseis",
    "3p": "pressentissem"
  },
  "FutSC": {
    "1s": "pressentir",
    "2s": "pressentires",
    "3s": "pressentir",
    "1p": "pressentirmos",
    "2p": "pressentirdes",
    "3p": "pressentirem"
  },
  "ImpA": {
    "1s": "",
    "2s": "pressente",
    "3s": "pressinta",
    "1p": "pressintamos",
    "2p": "pressenti",
    "3p": "pressintam"
  },
  "ImpN": {
    "1s": "",
    "2s": "não pressintas",
    "3s": "não pressinta",
    "1p": "não pressintamos",
    "2p": "não pressintais",
    "3p": "não pressintam"
  },
  "Part-ter": {
    "": "pressentido"
  },
  "Part-ser": {
    "ms": "pressentido",
    "fs": "pressentida",
    "mp": "pressentidos",
    "fp": "pressentidas"
  }
}