{
  "InfI": {
    "": "deslizar"
  },
  "InfP": {
    "1s": "deslizar",
    "2s": "deslizares",
    "3s": "deslizar",
    "1p": "deslizarmos",
    "2p": "deslizardes",
    "3p": "deslizarem"
  },
  "Ger": {
    "": "deslizando"
  },
  "PresI": {
    "1s": "deslizo",
    "2s": "deslizas",
    "3s": "desliza",
    "1p": "deslizamos",
    "2p": "deslizais",
    "3p": "deslizam"
  },
  "PImpI": {
    "1s": "deslizava",
    "2s": "deslizavas",
    "3s": "deslizava",
    "1p": "deslizávamos",
    "2p": "deslizáveis",
    "3p": "deslizavam"
  },
  "PPSI": {
    "1s": "deslizei",
    "2s": "deslizaste",
    "3s": "deslizou",
    "1p": "deslizámos",
    "2p": "deslizastes",
    "3p": "deslizaram"
  },
  "PMQPSI": {
    "1s": "deslizara",
    "2s": "deslizaras",
    "3s": "deslizara",
    "1p": "deslizáramos",
    "2p": "deslizáreis",
    "3p": "deslizaram"
  },
  "FutSI": {
    "1s": "deslizarei",
    "2s": "deslizarás",
    "3s": "deslizará",
    "1p": "deslizaremos",
    "2p": "deslizareis",
    "3p": "deslizarão"
  },
  "CondS": {
    "1s": "deslizaria",
    "2s": "deslizarias",
    "3s": "deslizaria",
    "1p": "deslizaríamos",
    "2p": "deslizaríeis",
    "3p": "deslizariam"
  },
  "PresC": {
    "1s": "deslize",
    "2s": "deslizes",
    "3s": "deslize",
    "1p": "deslizemos",
    "2p": "deslizeis",
    "3p": "deslizem"
  },
  "PImpC": {
    "1s": "deslizasse",
    "2s": "deslizasses",
    "3s": "deslizasse",
    "1p": "deslizássemos",
    "2p": "deslizásseis",
    "3p": "deslizassem"
  },
  "FutSC": {
    "1s": "deslizar",
    "2s": "deslizares",
    "3s": "deslizar",
    "1p": "deslizarmos",
    "2p": "deslizardes",
    "3p": "deslizarem"
  },
  "ImpA": {
    "1s": "",
    "2s": "desliza",
    "3s": "deslize",
    "1p": "deslizemos",
    "2p": "deslizai",
    "3p": "deslizem"
  },
  "ImpN": {
    "1s": "",
    "2s": "não deslizes",
    "3s": "não deslize",
    "1p": "não deslizemos",
    "2p": "não deslizeis",
    "3p": "não deslizem"
  },
  "Part-ter": {
    "": "deslizado"
  },
  "Part-ser": {
    "ms": "deslizado",
    "fs": "deslizada",
    "mp": "deslizados",
    "fp": "deslizadas"
  }
}