{
  "InfI": {
    "": "declinar"
  },
  "Ger": {
    "": "declinando"
  },
  "PresI": {
    "1s": "declino",
    "2s": "declinas",
    "3s": "declina",
    "1p": "declinamos",
    "2p": "declináis",
    "3p": "declinan"
  },
  "PImpI": {
    "1s": "declinaba",
    "2s": "declinabas",
    "3s": "declinaba",
    "1p": "declinábamos",
    "2p": "declinabais",
    "3p": "declinaban"
  },
  "PPSI": {
    "1s": "decliné",
    "2s": "declinaste",
    "3s": "declinó",
    "1p": "declinamos",
    "2p": "declinasteis",
    "3p": "declinaron"
  },
  "FutSI": {
    "1s": "declinaré",
    "2s": "declinarás",
    "3s": "declinará",
    "1p": "declinaremos",
    "2p": "declinaréis",
    "3p": "declinarán"
  },
  "CondS": {
    "1s": "declinaría",
    "2s": "declinarías",
    "3s": "declinaría",
    "1p": "declinaríamos",
    "2p": "declinaríais",
    "3p": "declinarían"
  },
  "PresC": {
    "1s": "decline",
    "2s": "declines",
    "3s": "decline",
    "1p": "declinemos",
    "2p": "declinéis",
    "3p": "declinen"
  },
  "PMQPSI": {
    "1s": "declinara",
    "2s": "declinaras",
    "3s": "declinara",
    "1p": "declináramos",
    "2p": "declinarais",
    "3p": "declinaran"
  },
  "PImpC": {
    "1s": "declinase",
    "2s": "declinases",
    "3s": "declinase",
    "1p": "declinásemos",
    "2p": "declinaseis",
    "3p": "declinasen"
  },
  "FutSC": {
    "1s": "declinare",
    "2s": "declinares",
    "3s": "declinare",
    "1p": "declináremos",
    "2p": "declinareis",
    "3p": "declinaren"
  },
  "ImpA": {
    "1s": "",
    "2s": "declina",
    "3s": "decline",
    "1p": "declinemos",
    "2p": "declinad",
    "3p": "declinen"
  },
  "ImpN": {
    "1s": "",
    "2s": "no declines",
    "3s": "no decline",
    "1p": "no declinemos",
    "2p": "no declinéis",
    "3p": "no declinen"
  },
  "Part-ter": {
    "": "declinado"
  },
  "Part-ser": {
    "ms": "declinado",
    "fs": "declinada",
    "mp": "declinados",
    "fp": "declinadas"
  }
}