{
  "InfI": {
    "": "descarriar"
  },
  "Ger": {
    "": "descarriando"
  },
  "PresI": {
    "1s": "descarrío",
    "2s": "descarrías",
    "3s": "descarría",
    "1p": "descarriamos",
    "2p": "descarriáis",
    "3p": "descarrían"
  },
  "PImpI": {
    "1s": "descarriaba",
    "2s": "descarriabas",
    "3s": "descarriaba",
    "1p": "descarriábamos",
    "2p": "descarriabais",
    "3p": "descarriaban"
  },
  "PPSI": {
    "1s": "descarrié",
    "2s": "descarriaste",
    "3s": "descarrió",
    "1p": "descarriamos",
    "2p": "descarriasteis",
    "3p": "descarriaron"
  },
  "FutSI": {
    "1s": "descarriaré",
    "2s": "descarriarás",
    "3s": "descarriará",
    "1p": "descarriaremos",
    "2p": "descarriaréis",
    "3p": "descarriarán"
  },
  "CondS": {
    "1s": "descarriaría",
    "2s": "descarriarías",
    "3s": "descarriaría",
    "1p": "descarriaríamos",
    "2p": "descarriaríais",
    "3p": "descarriarían"
  },
  "PresC": {
    "1s": "descarríe",
    "2s": "descarríes",
    "3s": "descarríe",
    "1p": "descarriemos",
    "2p": "descarriéis",
    "3p": "descarríen"
  },
  "PMQPSI": {
    "1s": "descarriara",
    "2s": "descarriaras",
    "3s": "descarriara",
    "1p": "descarriáramos",
    "2p": "descarriarais",
    "3p": "descarriaran"
  },
  "PImpC": {
    "1s": "descarriase",
    "2s": "descarriases",
    "3s": "descarriase",
    "1p": "descarriásemos",
    "2p": "descarriaseis",
    "3p": "descarriasen"
  },
  "FutSC": {
    "1s": "descarriare",
    "2s": "descarriares",
    "3s": "descarriare",
    "1p": "descarriáremos",
    "2p": "descarriareis",
    "3p": "descarriaren"
  },
  "ImpA": {
    "1s": "",
    "2s": "descarría",
    "3s": "descarríe",
    "1p": "descarriemos",
    "2p": "descarriad",
    "3p": "descarríen"
  },
  "ImpN": {
    "1s": "",
    "2s": "no descarríes",
    "3s": "no descarríe",
    "1p": "no descarriemos",
    "2p": "no descarriéis",
    "3p": "no descarríen"
  },
  "Part-ter": {
    "": "descarriado"
  },
  "Part-ser": {
    "ms": "descarriado",
    "fs": "descarriada",
    "mp": "descarriados",
    "fp": "descarriadas"
  }
}