{
  "InfI": {
    "": "difundir"
  },
  "Ger": {
    "": "difundiendo"
  },
  "PresI": {
    "1s": "difundo",
    "2s": "difundes",
    "3s": "difunde",
    "1p": "difundimos",
    "2p": "difundís",
    "3p": "difunden"
  },
  "PImpI": {
    "1s": "difundía",
    "2s": "difundías",
    "3s": "difundía",
    "1p": "difundíamos",
    "2p": "difundíais",
    "3p": "difundían"
  },
  "PPSI": {
    "1s": "difundí",
    "2s": "difundiste",
    "3s": "difundió",
    "1p": "difundimos",
    "2p": "difundisteis",
    "3p": "difundieron"
  },
  "FutSI": {
    "1s": "difundiré",
    "2s": "difundirás",
    "3s": "difundirá",
    "1p": "difundiremos",
    "2p": "difundiréis",
    "3p": "difundirán"
  },
  "CondS": {
    "1s": "difundiría",
    "2s": "difundirías",
    "3s": "difundiría",
    "1p": "difundiríamos",
    "2p": "difundiríais",
    "3p": "difundirían"
  },
  "PresC": {
    "1s": "difunda",
    "2s": "difundas",
    "3s": "difunda",
    "1p": "difundamos",
    "2p": "difundáis",
    "3p": "difundan"
  },
  "PMQPSI": {
    "1s": "difundiera",
    "2s": "difundieras",
    "3s": "difundiera",
    "1p": "difundiéramos",
    "2p": "difundierais",
    "3p": "difundieran"
  },
  "PImpC": {
    "1s": "difundiese",
    "2s": "difundieses",
    "3s": "difundiese",
    "1p": "difundiésemos",
    "2p": "difundieseis",
    "3p": "difundiesen"
  },
  "FutSC": {
    "1s": "difundiere",
    "2s": "difundieres",
    "3s": "difundiere",
    "1p": "difundiéremos",
    "2p": "difundiereis",
    "3p": "difundieren"
  },
  "ImpA": {
    "1s": "",
    "2s": "difunde",
    "3s": "difunda",
    "1p": "difundamos",
    "2p": "difundid",
    "3p": "difundan"
  },
  "ImpN": {
    "1s": "",
    "2s": "no difundas",
    "3s": "no difunda",
    "1p": "no difundamos",
    "2p": "no difundáis",
    "3p": "no difundan"
  },
  "Part-ter": {
    "": "difundido"
  },
  "Part-ser": {
    "ms": "difundido",
    "fs": "difundida",
    "mp": "difundidos",
    "fp": "difundidas"
  }
}