{
  "InfI": {
    "": "ejemplarizar"
  },
  "Ger": {
    "": "ejemplarizando"
  },
  "PresI": {
    "1s": "ejemplarizo",
    "2s": "ejemplarizas",
    "3s": "ejemplariza",
    "1p": "ejemplarizamos",
    "2p": "ejemplarizáis",
    "3p": "ejemplarizan"
  },
  "PImpI": {
    "1s": "ejemplarizaba",
    "2s": "ejemplarizabas",
    "3s": "ejemplarizaba",
    "1p": "ejemplarizábamos",
    "2p": "ejemplarizabais",
    "3p": "ejemplarizaban"
  },
  "PPSI": {
    "1s": "ejemplaricé",
    "2s": "ejemplarizaste",
    "3s": "ejemplarizó",
    "1p": "ejemplarizamos",
    "2p": "ejemplarizasteis",
    "3p": "ejemplarizaron"
  },
  "FutSI": {
    "1s": "ejemplarizaré",
    "2s": "ejemplarizarás",
    "3s": "ejemplarizará",
    "1p": "ejemplarizaremos",
    "2p": "ejemplarizaréis",
    "3p": "ejemplarizarán"
  },
  "CondS": {
    "1s": "ejemplarizaría",
    "2s": "ejemplarizarías",
    "3s": "ejemplarizaría",
    "1p": "ejemplarizaríamos",
    "2p": "ejemplarizaríais",
    "3p": "ejemplarizarían"
  },
  "PresC": {
    "1s": "ejemplarice",
    "2s": "ejemplarices",
    "3s": "ejemplarice",
    "1p": "ejemplaricemos",
    "2p": "ejemplaricéis",
    "3p": "ejemplaricen"
  },
  "PMQPSI": {
    "1s": "ejemplarizara",
    "2s": "ejemplarizaras",
    "3s": "ejemplarizara",
    "1p": "ejemplarizáramos",
    "2p": "ejemplarizarais",
    "3p": "ejemplarizaran"
  },
  "PImpC": {
    "1s": "ejemplarizase",
    "2s": "ejemplarizases",
    "3s": "ejemplarizase",
    "1p": "ejemplarizásemos",
    "2p": "ejemplarizaseis",
    "3p": "ejemplarizasen"
  },
  "FutSC": {
    "1s": "ejemplarizare",
    "2s": "ejemplarizares",
    "3s": "ejemplarizare",
    "1p": "ejemplarizáremos",
    "2p": "ejemplarizareis",
    "3p": "ejemplarizaren"
  },
  "ImpA": {
    "1s": "",
    "2s": "ejemplariza",
    "3s": "ejemplarice",
    "1p": "ejemplaricemos",
    "2p": "ejemplarizad",
    "3p": "ejemplaricen"
  },
  "ImpN": {
    "1s": "",
    "2s": "no ejemplarices",
    "3s": "no ejemplarice",
    "1p": "no ejemplaricemos",
    "2p": "no ejemplaricéis",
    "3p": "no ejemplaricen"
  },
  "Part-ter": {
    "": "ejemplarizado"
  },
  "Part-ser": {
    "ms": "ejemplarizado",
    "fs": "ejemplarizada",
    "mp": "ejemplarizados",
    "fp": "ejemplarizadas"
  }
}