{
  "InfI": {
    "": "congregar"
  },
  "InfP": {
    "1s": "congregar",
    "2s": "congregares",
    "3s": "congregar",
    "1p": "congregarmos",
    "2p": "congregardes",
    "3p": "congregarem"
  },
  "Ger": {
    "": "congregando"
  },
  "PresI": {
    "1s": "congrego",
    "2s": "congregas",
    "3s": "congrega",
    "1p": "congregamos",
    "2p": "congregais",
    "3p": "congregam"
  },
  "PImpI": {
    "1s": "congregava",
    "2s": "congregavas",
    "3s": "congregava",
    "1p": "congregávamos",
    "2p": "congregáveis",
    "3p": "congregavam"
  },
  "PPSI": {
    "1s": "congreguei",
    "2s": "congregaste",
    "3s": "congregou",
    "1p": "congregámos",
    "2p": "congregastes",
    "3p": "congregaram"
  },
  "PMQPSI": {
    "1s": "congregara",
    "2s": "congregaras",
    "3s": "congregara",
    "1p": "congregáramos",
    "2p": "congregáreis",
    "3p": "congregaram"
  },
  "FutSI": {
    "1s": "congregarei",
    "2s": "congregarás",
    "3s": "congregará",
    "1p": "congregaremos",
    "2p": "congregareis",
    "3p": "congregarão"
  },
  "CondS": {
    "1s": "congregaria",
    "2s": "congregarias",
    "3s": "congregaria",
    "1p": "congregaríamos",
    "2p": "congregaríeis",
    "3p": "congregariam"
  },
  "PresC": {
    "1s": "congregue",
    "2s": "congregues",
    "3s": "congregue",
    "1p": "congreguemos",
    "2p": "congregueis",
    "3p": "congreguem"
  },
  "PImpC": {
    "1s": "congregasse",
    "2s": "congregasses",
    "3s": "congregasse",
    "1p": "congregássemos",
    "2p": "congregásseis",
    "3p": "congregassem"
  },
  "FutSC": {
    "1s": "congregar",
    "2s": "congregares",
    "3s": "congregar",
    "1p": "congregarmos",
    "2p": "congregardes",
    "3p": "congregarem"
  },
  "ImpA": {
    "1s": "",
    "2s": "congrega",
    "3s": "congregue",
    "1p": "congreguemos",
    "2p": "congregai",
    "3p": "congreguem"
  },
  "ImpN": {
    "1s": "",
    "2s": "não congregues",
    "3s": "não congregue",
    "1p": "não congreguemos",
    "2p": "não congregueis",
    "3p": "não congreguem"
  },
  "Part-ter": {
    "": "congregado"
  },
  "Part-ser": {
    "ms": "congregado",
    "fs": "congregada",
    "mp": "congregados",
    "fp": "congregadas"
  }
}