{
  "InfI": {
    "": "sorprender"
  },
  "Ger": {
    "": "sorprendiendo"
  },
  "PresI": {
    "1s": "sorprendo",
    "2s": "sorprendes",
    "3s": "sorprende",
    "1p": "sorprendemos",
    "2p": "sorprendéis",
    "3p": "sorprenden"
  },
  "PImpI": {
    "1s": "sorprendía",
    "2s": "sorprendías",
    "3s": "sorprendía",
    "1p": "sorprendíamos",
    "2p": "sorprendíais",
    "3p": "sorprendían"
  },
  "PPSI": {
    "1s": "sorprendí",
    "2s": "sorprendiste",
    "3s": "sorprendió",
    "1p": "sorprendimos",
    "2p": "sorprendisteis",
    "3p": "sorprendieron"
  },
  "FutSI": {
    "1s": "sorprenderé",
    "2s": "sorprenderás",
    "3s": "sorprenderá",
    "1p": "sorprenderemos",
    "2p": "sorprenderéis",
    "3p": "sorprenderán"
  },
  "CondS": {
    "1s": "sorprendería",
    "2s": "sorprenderías",
    "3s": "sorprendería",
    "1p": "sorprenderíamos",
    "2p": "sorprenderíais",
    "3p": "sorprenderían"
  },
  "PresC": {
    "1s": "sorprenda",
    "2s": "sorprendas",
    "3s": "sorprenda",
    "1p": "sorprendamos",
    "2p": "sorprendáis",
    "3p": "sorprendan"
  },
  "PMQPSI": {
    "1s": "sorprendiera",
    "2s": "sorprendieras",
    "3s": "sorprendiera",
    "1p": "sorprendiéramos",
    "2p": "sorprendierais",
    "3p": "sorprendieran"
  },
  "PImpC": {
    "1s": "sorprendiese",
    "2s": "sorprendieses",
    "3s": "sorprendiese",
    "1p": "sorprendiésemos",
    "2p": "sorprendieseis",
    "3p": "sorprendiesen"
  },
  "FutSC": {
    "1s": "sorprendiere",
    "2s": "sorprendieres",
    "3s": "sorprendiere",
    "1p": "sorprendiéremos",
    "2p": "sorprendiereis",
    "3p": "sorprendieren"
  },
  "ImpA": {
    "1s": "",
    "2s": "sorprende",
    "3s": "sorprenda",
    "1p": "sorprendamos",
    "2p": "sorprended",
    "3p": "sorprendan"
  },
  "ImpN": {
    "1s": "",
    "2s": "no sorprendas",
    "3s": "no sorprenda",
    "1p": "no sorprendamos",
    "2p": "no sorprendáis",
    "3p": "no sorprendan"
  },
  "Part-ter": {
    "": "sorprendido"
  },
  "Part-ser": {
    "ms": "sorprendido",
    "fs": "sorprendida",
    "mp": "sorprendidos",
    "fp": "sorprendidas"
  }
}