{
  "InfI": {
    "": "odorizar"
  },
  "InfP": {
    "1s": "odorizar",
    "2s": "odorizares",
    "3s": "odorizar",
    "1p": "odorizarmos",
    "2p": "odorizardes",
    "3p": "odorizarem"
  },
  "Ger": {
    "": "odorizando"
  },
  "PresI": {
    "1s": "odorizo",
    "2s": "odorizas",
    "3s": "odoriza",
    "1p": "odorizamos",
    "2p": "odorizais",
    "3p": "odorizam"
  },
  "PImpI": {
    "1s": "odorizava",
    "2s": "odorizavas",
    "3s": "odorizava",
    "1p": "odorizávamos",
    "2p": "odorizáveis",
    "3p": "odorizavam"
  },
  "PPSI": {
    "1s": "odorizei",
    "2s": "odorizaste",
    "3s": "odorizou",
    "1p": "odorizámos",
    "2p": "odorizastes",
    "3p": "odorizaram"
  },
  "PMQPSI": {
    "1s": "odorizara",
    "2s": "odorizaras",
    "3s": "odorizara",
    "1p": "odorizáramos",
    "2p": "odorizáreis",
    "3p": "odorizaram"
  },
  "FutSI": {
    "1s": "odorizarei",
    "2s": "odorizarás",
    "3s": "odorizará",
    "1p": "odorizaremos",
    "2p": "odorizareis",
    "3p": "odorizarão"
  },
  "CondS": {
    "1s": "odorizaria",
    "2s": "odorizarias",
    "3s": "odorizaria",
    "1p": "odorizaríamos",
    "2p": "odorizaríeis",
    "3p": "odorizariam"
  },
  "PresC": {
    "1s": "odorize",
    "2s": "odorizes",
    "3s": "odorize",
    "1p": "odorizemos",
    "2p": "odorizeis",
    "3p": "odorizem"
  },
  "PImpC": {
    "1s": "odorizasse",
    "2s": "odorizasses",
    "3s": "odorizasse",
    "1p": "odorizássemos",
    "2p": "odorizásseis",
    "3p": "odorizassem"
  },
  "FutSC": {
    "1s": "odorizar",
    "2s": "odorizares",
    "3s": "odorizar",
    "1p": "odorizarmos",
    "2p": "odorizardes",
    "3p": "odorizarem"
  },
  "ImpA": {
    "1s": "",
    "2s": "odoriza",
    "3s": "odorize",
    "1p": "odorizemos",
    "2p": "odorizai",
    "3p": "odorizem"
  },
  "ImpN": {
    "1s": "",
    "2s": "não odorizes",
    "3s": "não odorize",
    "1p": "não odorizemos",
    "2p": "não odorizeis",
    "3p": "não odorizem"
  },
  "Part-ter": {
    "": "odorizado"
  },
  "Part-ser": {
    "ms": "odorizado",
    "fs": "odorizada",
    "mp": "odorizados",
    "fp": "odorizadas"
  }
}