{
  "InfI": {
    "": "recolonizar"
  },
  "Ger": {
    "": "recolonizando"
  },
  "PresI": {
    "1s": "recolonizo",
    "2s": "recolonizas",
    "3s": "recoloniza",
    "1p": "recolonizamos",
    "2p": "recolonizáis",
    "3p": "recolonizan"
  },
  "PImpI": {
    "1s": "recolonizaba",
    "2s": "recolonizabas",
    "3s": "recolonizaba",
    "1p": "recolonizábamos",
    "2p": "recolonizabais",
    "3p": "recolonizaban"
  },
  "PPSI": {
    "1s": "recolonicé",
    "2s": "recolonizaste",
    "3s": "recolonizó",
    "1p": "recolonizamos",
    "2p": "recolonizasteis",
    "3p": "recolonizaron"
  },
  "FutSI": {
    "1s": "recolonizaré",
    "2s": "recolonizarás",
    "3s": "recolonizará",
    "1p": "recolonizaremos",
    "2p": "recolonizaréis",
    "3p": "recolonizarán"
  },
  "CondS": {
    "1s": "recolonizaría",
    "2s": "recolonizarías",
    "3s": "recolonizaría",
    "1p": "recolonizaríamos",
    "2p": "recolonizaríais",
    "3p": "recolonizarían"
  },
  "PresC": {
    "1s": "recolonice",
    "2s": "recolonices",
    "3s": "recolonice",
    "1p": "recolonicemos",
    "2p": "recolonicéis",
    "3p": "recolonicen"
  },
  "PMQPSI": {
    "1s": "recolonizara",
    "2s": "recolonizaras",
    "3s": "recolonizara",
    "1p": "recolonizáramos",
    "2p": "recolonizarais",
    "3p": "recolonizaran"
  },
  "PImpC": {
    "1s": "recolonizase",
    "2s": "recolonizases",
    "3s": "recolonizase",
    "1p": "recolonizásemos",
    "2p": "recolonizaseis",
    "3p": "recolonizasen"
  },
  "FutSC": {
    "1s": "recolonizare",
    "2s": "recolonizares",
    "3s": "recolonizare",
    "1p": "recolonizáremos",
    "2p": "recolonizareis",
    "3p": "recolonizaren"
  },
  "ImpA": {
    "1s": "",
    "2s": "recoloniza",
    "3s": "recolonice",
    "1p": "recolonicemos",
    "2p": "recolonizad",
    "3p": "recolonicen"
  },
  "ImpN": {
    "1s": "",
    "2s": "no recolonices",
    "3s": "no recolonice",
    "1p": "no recolonicemos",
    "2p": "no recolonicéis",
    "3p": "no recolonicen"
  },
  "Part-ter": {
    "": "recolonizado"
  },
  "Part-ser": {
    "ms": "recolonizado",
    "fs": "recolonizada",
    "mp": "recolonizados",
    "fp": "recolonizadas"
  }
}