{
  "InfI": {
    "": "reenterrar"
  },
  "Ger": {
    "": "reenterrando"
  },
  "PresI": {
    "1s": "reentierro",
    "2s": "reentierras",
    "3s": "reentierra",
    "1p": "reenterramos",
    "2p": "reenterráis",
    "3p": "reentierran"
  },
  "PImpI": {
    "1s": "reenterraba",
    "2s": "reenterrabas",
    "3s": "reenterraba",
    "1p": "reenterrábamos",
    "2p": "reenterrabais",
    "3p": "reenterraban"
  },
  "PPSI": {
    "1s": "reenterré",
    "2s": "reenterraste",
    "3s": "reenterró",
    "1p": "reenterramos",
    "2p": "reenterrasteis",
    "3p": "reenterraron"
  },
  "FutSI": {
    "1s": "reenterraré",
    "2s": "reenterrarás",
    "3s": "reenterrará",
    "1p": "reenterraremos",
    "2p": "reenterraréis",
    "3p": "reenterrarán"
  },
  "CondS": {
    "1s": "reenterraría",
    "2s": "reenterrarías",
    "3s": "reenterraría",
    "1p": "reenterraríamos",
    "2p": "reenterraríais",
    "3p": "reenterrarían"
  },
  "PresC": {
    "1s": "reentierre",
    "2s": "reentierres",
    "3s": "reentierre",
    "1p": "reenterremos",
    "2p": "reenterréis",
    "3p": "reentierren"
  },
  "PMQPSI": {
    "1s": "reenterrara",
    "2s": "reenterraras",
    "3s": "reenterrara",
    "1p": "reenterráramos",
    "2p": "reenterrarais",
    "3p": "reenterraran"
  },
  "PImpC": {
    "1s": "reenterrase",
    "2s": "reenterrases",
    "3s": "reenterrase",
    "1p": "reenterrásemos",
    "2p": "reenterraseis",
    "3p": "reenterrasen"
  },
  "FutSC": {
    "1s": "reenterrare",
    "2s": "reenterrares",
    "3s": "reenterrare",
    "1p": "reenterráremos",
    "2p": "reenterrareis",
    "3p": "reenterraren"
  },
  "ImpA": {
    "1s": "",
    "2s": "reentierra",
    "3s": "reentierre",
    "1p": "reenterremos",
    "2p": "reenterrad",
    "3p": "reentierren"
  },
  "ImpN": {
    "1s": "",
    "2s": "no reentierres",
    "3s": "no reentierre",
    "1p": "no reenterremos",
    "2p": "no reenterréis",
    "3p": "no reentierren"
  },
  "Part-ter": {
    "": "reenterrado"
  },
  "Part-ser": {
    "ms": "reenterrado",
    "fs": "reenterrada",
    "mp": "reenterrados",
    "fp": "reenterradas"
  }
}