{
  "InfI": {
    "": "resignificar"
  },
  "Ger": {
    "": "resignificando"
  },
  "PresI": {
    "1s": "resignifico",
    "2s": "resignificas",
    "3s": "resignifica",
    "1p": "resignificamos",
    "2p": "resignificáis",
    "3p": "resignifican"
  },
  "PImpI": {
    "1s": "resignificaba",
    "2s": "resignificabas",
    "3s": "resignificaba",
    "1p": "resignificábamos",
    "2p": "resignificabais",
    "3p": "resignificaban"
  },
  "PPSI": {
    "1s": "resignifiqué",
    "2s": "resignificaste",
    "3s": "resignificó",
    "1p": "resignificamos",
    "2p": "resignificasteis",
    "3p": "resignificaron"
  },
  "FutSI": {
    "1s": "resignificaré",
    "2s": "resignificarás",
    "3s": "resignificará",
    "1p": "resignificaremos",
    "2p": "resignificaréis",
    "3p": "resignificarán"
  },
  "CondS": {
    "1s": "resignificaría",
    "2s": "resignificarías",
    "3s": "resignificaría",
    "1p": "resignificaríamos",
    "2p": "resignificaríais",
    "3p": "resignificarían"
  },
  "PresC": {
    "1s": "resignifique",
    "2s": "resignifiques",
    "3s": "resignifique",
    "1p": "resignifiquemos",
    "2p": "resignifiquéis",
    "3p": "resignifiquen"
  },
  "PMQPSI": {
    "1s": "resignificara",
    "2s": "resignificaras",
    "3s": "resignificara",
    "1p": "resignificáramos",
    "2p": "resignificarais",
    "3p": "resignificaran"
  },
  "PImpC": {
    "1s": "resignificase",
    "2s": "resignificases",
    "3s": "resignificase",
    "1p": "resignificásemos",
    "2p": "resignificaseis",
    "3p": "resignificasen"
  },
  "FutSC": {
    "1s": "resignificare",
    "2s": "resignificares",
    "3s": "resignificare",
    "1p": "resignificáremos",
    "2p": "resignificareis",
    "3p": "resignificaren"
  },
  "ImpA": {
    "1s": "",
    "2s": "resignifica",
    "3s": "resignifique",
    "1p": "resignifiquemos",
    "2p": "resignificad",
    "3p": "resignifiquen"
  },
  "ImpN": {
    "1s": "",
    "2s": "no resignifiques",
    "3s": "no resignifique",
    "1p": "no resignifiquemos",
    "2p": "no resignifiquéis",
    "3p": "no resignifiquen"
  },
  "Part-ter": {
    "": "resignificado"
  },
  "Part-ser": {
    "ms": "resignificado",
    "fs": "resignificada",
    "mp": "resignificados",
    "fp": "resignificadas"
  }
}