{
  "InfI": {
    "": "cuidarse"
  },
  "Ger": {
    "": "cuidándose"
  },
  "PresI": {
    "1s": "me cuido",
    "2s": "te cuidas",
    "3s": "se cuida",
    "1p": "nos cuidamos",
    "2p": "os cuidáis",
    "3p": "se cuidan"
  },
  "PImpI": {
    "1s": "me cuidaba",
    "2s": "te cuidabas",
    "3s": "se cuidaba",
    "1p": "nos cuidábamos",
    "2p": "os cuidabais",
    "3p": "se cuidaban"
  },
  "PPSI": {
    "1s": "me cuidé",
    "2s": "te cuidaste",
    "3s": "se cuidó",
    "1p": "nos cuidamos",
    "2p": "os cuidasteis",
    "3p": "se cuidaron"
  },
  "FutSI": {
    "1s": "me cuidaré",
    "2s": "te cuidarás",
    "3s": "se cuidará",
    "1p": "nos cuidaremos",
    "2p": "os cuidaréis",
    "3p": "se cuidarán"
  },
  "CondS": {
    "1s": "me cuidaría",
    "2s": "te cuidarías",
    "3s": "se cuidaría",
    "1p": "nos cuidaríamos",
    "2p": "os cuidaríais",
    "3p": "se cuidarían"
  },
  "PresC": {
    "1s": "me cuide",
    "2s": "te cuides",
    "3s": "se cuide",
    "1p": "nos cuidemos",
    "2p": "os cuidéis",
    "3p": "se cuiden"
  },
  "PMQPSI": {
    "1s": "me cuidara",
    "2s": "te cuidaras",
    "3s": "se cuidara",
    "1p": "nos cuidáramos",
    "2p": "os cuidarais",
    "3p": "se cuidaran"
  },
  "PImpC": {
    "1s": "me cuidase",
    "2s": "te cuidases",
    "3s": "se cuidase",
    "1p": "nos cuidásemos",
    "2p": "os cuidaseis",
    "3p": "se cuidasen"
  },
  "FutSC": {
    "1s": "me cuidare",
    "2s": "te cuidares",
    "3s": "se cuidare",
    "1p": "nos cuidáremos",
    "2p": "os cuidareis",
    "3p": "se cuidaren"
  },
  "ImpA": {
    "1s": "",
    "2s": "cuídate",
    "3s": "cuídese",
    "1p": "cuidémonos",
    "2p": "cuidaos",
    "3p": "cuídense"
  },
  "ImpN": {
    "1s": "",
    "2s": "no te cuides",
    "3s": "no se cuide",
    "1p": "no nos cuidemos",
    "2p": "no os cuidéis",
    "3p": "no se cuiden"
  },
  "Part-ter": {
    "": "cuidado"
  },
  "Part-ser": {
    "ms": "cuidado",
    "fs": "cuidada",
    "mp": "cuidados",
    "fp": "cuidadas"
  }
}