{
  "InfI": {
    "": "patrimonializar"
  },
  "Ger": {
    "": "patrimonializando"
  },
  "PresI": {
    "1s": "patrimonializo",
    "2s": "patrimonializas",
    "3s": "patrimonializa",
    "1p": "patrimonializamos",
    "2p": "patrimonializáis",
    "3p": "patrimonializan"
  },
  "PImpI": {
    "1s": "patrimonializaba",
    "2s": "patrimonializabas",
    "3s": "patrimonializaba",
    "1p": "patrimonializábamos",
    "2p": "patrimonializabais",
    "3p": "patrimonializaban"
  },
  "PPSI": {
    "1s": "patrimonialicé",
    "2s": "patrimonializaste",
    "3s": "patrimonializó",
    "1p": "patrimonializamos",
    "2p": "patrimonializasteis",
    "3p": "patrimonializaron"
  },
  "FutSI": {
    "1s": "patrimonializaré",
    "2s": "patrimonializarás",
    "3s": "patrimonializará",
    "1p": "patrimonializaremos",
    "2p": "patrimonializaréis",
    "3p": "patrimonializarán"
  },
  "CondS": {
    "1s": "patrimonializaría",
    "2s": "patrimonializarías",
    "3s": "patrimonializaría",
    "1p": "patrimonializaríamos",
    "2p": "patrimonializaríais",
    "3p": "patrimonializarían"
  },
  "PresC": {
    "1s": "patrimonialice",
    "2s": "patrimonialices",
    "3s": "patrimonialice",
    "1p": "patrimonialicemos",
    "2p": "patrimonialicéis",
    "3p": "patrimonialicen"
  },
  "PMQPSI": {
    "1s": "patrimonializara",
    "2s": "patrimonializaras",
    "3s": "patrimonializara",
    "1p": "patrimonializáramos",
    "2p": "patrimonializarais",
    "3p": "patrimonializaran"
  },
  "PImpC": {
    "1s": "patrimonializase",
    "2s": "patrimonializases",
    "3s": "patrimonializase",
    "1p": "patrimonializásemos",
    "2p": "patrimonializaseis",
    "3p": "patrimonializasen"
  },
  "FutSC": {
    "1s": "patrimonializare",
    "2s": "patrimonializares",
    "3s": "patrimonializare",
    "1p": "patrimonializáremos",
    "2p": "patrimonializareis",
    "3p": "patrimonializaren"
  },
  "ImpA": {
    "1s": "",
    "2s": "patrimonializa",
    "3s": "patrimonialice",
    "1p": "patrimonialicemos",
    "2p": "patrimonializad",
    "3p": "patrimonialicen"
  },
  "ImpN": {
    "1s": "",
    "2s": "no patrimonialices",
    "3s": "no patrimonialice",
    "1p": "no patrimonialicemos",
    "2p": "no patrimonialicéis",
    "3p": "no patrimonialicen"
  },
  "Part-ter": {
    "": "patrimonializado"
  },
  "Part-ser": {
    "ms": "patrimonializado",
    "fs": "patrimonializada",
    "mp": "patrimonializados",
    "fp": "patrimonializadas"
  }
}