{
  "InfI": {
    "": "postular"
  },
  "Ger": {
    "": "postulando"
  },
  "PresI": {
    "1s": "postulo",
    "2s": "postulas",
    "3s": "postula",
    "1p": "postulamos",
    "2p": "postuláis",
    "3p": "postulan"
  },
  "PImpI": {
    "1s": "postulaba",
    "2s": "postulabas",
    "3s": "postulaba",
    "1p": "postulábamos",
    "2p": "postulabais",
    "3p": "postulaban"
  },
  "PPSI": {
    "1s": "postulé",
    "2s": "postulaste",
    "3s": "postuló",
    "1p": "postulamos",
    "2p": "postulasteis",
    "3p": "postularon"
  },
  "FutSI": {
    "1s": "postularé",
    "2s": "postularás",
    "3s": "postulará",
    "1p": "postularemos",
    "2p": "postularéis",
    "3p": "postularán"
  },
  "CondS": {
    "1s": "postularía",
    "2s": "postularías",
    "3s": "postularía",
    "1p": "postularíamos",
    "2p": "postularíais",
    "3p": "postularían"
  },
  "PresC": {
    "1s": "postule",
    "2s": "postules",
    "3s": "postule",
    "1p": "postulemos",
    "2p": "postuléis",
    "3p": "postulen"
  },
  "PMQPSI": {
    "1s": "postulara",
    "2s": "postularas",
    "3s": "postulara",
    "1p": "postuláramos",
    "2p": "postularais",
    "3p": "postularan"
  },
  "PImpC": {
    "1s": "postulase",
    "2s": "postulases",
    "3s": "postulase",
    "1p": "postulásemos",
    "2p": "postulaseis",
    "3p": "postulasen"
  },
  "FutSC": {
    "1s": "postulare",
    "2s": "postulares",
    "3s": "postulare",
    "1p": "postuláremos",
    "2p": "postulareis",
    "3p": "postularen"
  },
  "ImpA": {
    "1s": "",
    "2s": "postula",
    "3s": "postule",
    "1p": "postulemos",
    "2p": "postulad",
    "3p": "postulen"
  },
  "ImpN": {
    "1s": "",
    "2s": "no postules",
    "3s": "no postule",
    "1p": "no postulemos",
    "2p": "no postuléis",
    "3p": "no postulen"
  },
  "Part-ter": {
    "": "postulado"
  },
  "Part-ser": {
    "ms": "postulado",
    "fs": "postulada",
    "mp": "postulados",
    "fp": "postuladas"
  }
}