{
  "InfI": {
    "": "aberrar"
  },
  "Ger": {
    "": "aberrando"
  },
  "PresI": {
    "1s": "aberro",
    "2s": "aberras",
    "3s": "aberra",
    "1p": "aberramos",
    "2p": "aberráis",
    "3p": "aberran"
  },
  "PImpI": {
    "1s": "aberraba",
    "2s": "aberrabas",
    "3s": "aberraba",
    "1p": "aberrábamos",
    "2p": "aberrabais",
    "3p": "aberraban"
  },
  "PPSI": {
    "1s": "aberré",
    "2s": "aberraste",
    "3s": "aberró",
    "1p": "aberramos",
    "2p": "aberrasteis",
    "3p": "aberraron"
  },
  "FutSI": {
    "1s": "aberraré",
    "2s": "aberrarás",
    "3s": "aberrará",
    "1p": "aberraremos",
    "2p": "aberraréis",
    "3p": "aberrarán"
  },
  "CondS": {
    "1s": "aberraría",
    "2s": "aberrarías",
    "3s": "aberraría",
    "1p": "aberraríamos",
    "2p": "aberraríais",
    "3p": "aberrarían"
  },
  "PresC": {
    "1s": "aberre",
    "2s": "aberres",
    "3s": "aberre",
    "1p": "aberremos",
    "2p": "aberréis",
    "3p": "aberren"
  },
  "PMQPSI": {
    "1s": "aberrara",
    "2s": "aberraras",
    "3s": "aberrara",
    "1p": "aberráramos",
    "2p": "aberrarais",
    "3p": "aberraran"
  },
  "PImpC": {
    "1s": "aberrase",
    "2s": "aberrases",
    "3s": "aberrase",
    "1p": "aberrásemos",
    "2p": "aberraseis",
    "3p": "aberrasen"
  },
  "FutSC": {
    "1s": "aberrare",
    "2s": "aberrares",
    "3s": "aberrare",
    "1p": "aberráremos",
    "2p": "aberrareis",
    "3p": "aberraren"
  },
  "ImpA": {
    "1s": "",
    "2s": "aberra",
    "3s": "aberre",
    "1p": "aberremos",
    "2p": "aberrad",
    "3p": "aberren"
  },
  "ImpN": {
    "1s": "",
    "2s": "no aberres",
    "3s": "no aberre",
    "1p": "no aberremos",
    "2p": "no aberréis",
    "3p": "no aberren"
  },
  "Part-ter": {
    "": "aberrado"
  },
  "Part-ser": {
    "ms": "aberrado",
    "fs": "aberrada",
    "mp": "aberrados",
    "fp": "aberradas"
  }
}