{
  "InfI": {
    "": "triunfar"
  },
  "InfP": {
    "1s": "triunfar",
    "2s": "triunfares",
    "3s": "triunfar",
    "1p": "triunfarmos",
    "2p": "triunfardes",
    "3p": "triunfarem"
  },
  "Ger": {
    "": "triunfando"
  },
  "PresI": {
    "1s": "triunfo",
    "2s": "triunfas",
    "3s": "triunfa",
    "1p": "triunfamos",
    "2p": "triunfais",
    "3p": "triunfam"
  },
  "PImpI": {
    "1s": "triunfava",
    "2s": "triunfavas",
    "3s": "triunfava",
    "1p": "triunfávamos",
    "2p": "triunfáveis",
    "3p": "triunfavam"
  },
  "PPSI": {
    "1s": "triunfei",
    "2s": "triunfaste",
    "3s": "triunfou",
    "1p": "triunfámos",
    "2p": "triunfastes",
    "3p": "triunfaram"
  },
  "PMQPSI": {
    "1s": "triunfara",
    "2s": "triunfaras",
    "3s": "triunfara",
    "1p": "triunfáramos",
    "2p": "triunfáreis",
    "3p": "triunfaram"
  },
  "FutSI": {
    "1s": "triunfarei",
    "2s": "triunfarás",
    "3s": "triunfará",
    "1p": "triunfaremos",
    "2p": "triunfareis",
    "3p": "triunfarão"
  },
  "CondS": {
    "1s": "triunfaria",
    "2s": "triunfarias",
    "3s": "triunfaria",
    "1p": "triunfaríamos",
    "2p": "triunfaríeis",
    "3p": "triunfariam"
  },
  "PresC": {
    "1s": "triunfe",
    "2s": "triunfes",
    "3s": "triunfe",
    "1p": "triunfemos",
    "2p": "triunfeis",
    "3p": "triunfem"
  },
  "PImpC": {
    "1s": "triunfasse",
    "2s": "triunfasses",
    "3s": "triunfasse",
    "1p": "triunfássemos",
    "2p": "triunfásseis",
    "3p": "triunfassem"
  },
  "FutSC": {
    "1s": "triunfar",
    "2s": "triunfares",
    "3s": "triunfar",
    "1p": "triunfarmos",
    "2p": "triunfardes",
    "3p": "triunfarem"
  },
  "ImpA": {
    "1s": "",
    "2s": "triunfa",
    "3s": "triunfe",
    "1p": "triunfemos",
    "2p": "triunfai",
    "3p": "triunfem"
  },
  "ImpN": {
    "1s": "",
    "2s": "não triunfes",
    "3s": "não triunfe",
    "1p": "não triunfemos",
    "2p": "não triunfeis",
    "3p": "não triunfem"
  },
  "Part-ter": {
    "": "triunfado"
  },
  "Part-ser": {
    "ms": "triunfado",
    "fs": "triunfada",
    "mp": "triunfados",
    "fp": "triunfadas"
  }
}