{
  "InfI": {
    "": "familiarizar"
  },
  "Ger": {
    "": "familiarizando"
  },
  "PresI": {
    "1s": "familiarizo",
    "2s": "familiarizas",
    "3s": "familiariza",
    "1p": "familiarizamos",
    "2p": "familiarizáis",
    "3p": "familiarizan"
  },
  "PImpI": {
    "1s": "familiarizaba",
    "2s": "familiarizabas",
    "3s": "familiarizaba",
    "1p": "familiarizábamos",
    "2p": "familiarizabais",
    "3p": "familiarizaban"
  },
  "PPSI": {
    "1s": "familiaricé",
    "2s": "familiarizaste",
    "3s": "familiarizó",
    "1p": "familiarizamos",
    "2p": "familiarizasteis",
    "3p": "familiarizaron"
  },
  "FutSI": {
    "1s": "familiarizaré",
    "2s": "familiarizarás",
    "3s": "familiarizará",
    "1p": "familiarizaremos",
    "2p": "familiarizaréis",
    "3p": "familiarizarán"
  },
  "CondS": {
    "1s": "familiarizaría",
    "2s": "familiarizarías",
    "3s": "familiarizaría",
    "1p": "familiarizaríamos",
    "2p": "familiarizaríais",
    "3p": "familiarizarían"
  },
  "PresC": {
    "1s": "familiarice",
    "2s": "familiarices",
    "3s": "familiarice",
    "1p": "familiaricemos",
    "2p": "familiaricéis",
    "3p": "familiaricen"
  },
  "PMQPSI": {
    "1s": "familiarizara",
    "2s": "familiarizaras",
    "3s": "familiarizara",
    "1p": "familiarizáramos",
    "2p": "familiarizarais",
    "3p": "familiarizaran"
  },
  "PImpC": {
    "1s": "familiarizase",
    "2s": "familiarizases",
    "3s": "familiarizase",
    "1p": "familiarizásemos",
    "2p": "familiarizaseis",
    "3p": "familiarizasen"
  },
  "FutSC": {
    "1s": "familiarizare",
    "2s": "familiarizares",
    "3s": "familiarizare",
    "1p": "familiarizáremos",
    "2p": "familiarizareis",
    "3p": "familiarizaren"
  },
  "ImpA": {
    "1s": "",
    "2s": "familiariza",
    "3s": "familiarice",
    "1p": "familiaricemos",
    "2p": "familiarizad",
    "3p": "familiaricen"
  },
  "ImpN": {
    "1s": "",
    "2s": "no familiarices",
    "3s": "no familiarice",
    "1p": "no familiaricemos",
    "2p": "no familiaricéis",
    "3p": "no familiaricen"
  },
  "Part-ter": {
    "": "familiarizado"
  },
  "Part-ser": {
    "ms": "familiarizado",
    "fs": "familiarizada",
    "mp": "familiarizados",
    "fp": "familiarizadas"
  }
}